JaxDecompiler/decompiler.py
JaxDecompiler/primitive_mapping.py
JaxDecompiler-0.0.6.dist-info/LICENSE
JaxDecompiler-0.0.6.dist-info/METADATA
JaxDecompiler-0.0.6.dist-info/WHEEL
JaxDecompiler-0.0.6.dist-info/top_level.txt
JaxDecompiler-0.0.6.dist-info/RECORD
